setup.py
tina/__init__.py
tina/berkslib.py
tina/cookbook_metadata.py
tina/cookbook_repo.py
tina/gitlib.py
tina/tag.py
tina/tina.py
tina/tina_util.py
tina/version_requirement.py
tina.egg-info/PKG-INFO
tina.egg-info/SOURCES.txt
tina.egg-info/dependency_links.txt
tina.egg-info/entry_points.txt
tina.egg-info/top_level.txt