Metadata-Version: 1.0
Name: tina
Version: 0.6
Summary: TINA Is Not Arif: A tool for tagging chef cookbooks and their dependencies.
Home-page: https://github.com/RSEmail/tina/
Author: RSEmail
Author-email: tina-dev@mailtrust.com
License: GNU General Public License, version 3 (GPL-3.0)
Platform: UNKNOWN
